[
    {
        "name": "adbch.top",
        "status": "free",
        "register": "https://adbch.top/r/110267",
        "download": "https://exe.io/gHY1K",
        "media": "https://www.mediafire.com/folder/i2czymc5agh84/adbch.top",
        "date": 1763642216
    },
    {
        "name": "beefaucet.org",
        "status": "apikey",
        "register": "https://beefaucet.org/bnb-faucet/?r=purna.iera@gmail.com",
        "download": "https://exe.io/US1InGXq",
        "media": "https://www.mediafire.com/folder/b0u79i6l5jx9f/beefaucet.org",
        "date": 1764264639
    },
    {
        "name": "brunoplay",
        "version": "0.0.2",
        "status": "free",
        "register": "https://t.me/BrunoPlay_bot/Bruno?startapp=ref_513",
        "description": "new bruno",
        "download": "https://exe.io/T0CHjmI9",
        "media": "https://www.mediafire.com/folder/mef4kcsn9o9b6/brunoplay",
        "date": 1766222443
    },
    {
        "name": "claimfreecoins.io",
        "status": "apikey",
        "register": "https://claimfreecoins.io/bitcoin-faucet/?r=purna.iera@gmail.com",
        "download": "https://exe.io/8FXPHOE",
        "media": "https://www.mediafire.com/folder/5rvv298535zu9/claimfreecoins.io",
        "date": 1763988035
    },
    {
        "name": "clxaward.com",
        "status": "apikey",
        "register": "https://clxaward.com/ref/iewilmaestro",
        "download": "https://exe.io/kM1BBy4",
        "media": "https://www.mediafire.com/folder/vjn29tskvqi28/clxaward.com",
        "date": 1764095825
    },
    {
        "name": "coinpin.top",
        "status": "free",
        "register": "https://coinpin.top/?r=5345",
        "download": "https://exe.io/HLdfkt",
        "media": "https://www.mediafire.com/folder/kn6brnsfpq6o5/coinpin.top",
        "date": 1764128147
    },
    {
        "name": "crypto-marvelgame.net",
        "status": "free",
        "register": "https://crypto-marvelgame.net/?ref=anjim128",
        "download": "https://exe.io/DBH8F",
        "media": "https://www.mediafire.com/folder/y7mv4i7817ca5/crypto-marvelgame.net",
        "date": 1763645824
    },
    {
        "name": "firefaucet.win",
        "status": "apikey",
        "register": "https://firefaucet.win/ref/1258480",
        "download": "https://exe.io/ocqBR",
        "media": "https://www.mediafire.com/folder/tjdnsuaxybtbr/firefaucet.win",
        "date": 1763963890
    },
    {
        "name": "ourcoincash.xyz",
        "status": "apikey",
        "register": "https://ourcoincash.xyz/?r=3408",
        "download": "https://exe.io/Z3BlWz9j",
        "media": "https://www.mediafire.com/folder/0rytj9a06u87i/ourcoincash.xyz",
        "date": 1765681334,
        "version": "0.0.2",
        "description": "fix bug ptc"
    },
    {
        "name": "serfclick.net",
        "status": "free",
        "register": "https://serfclick.net/i/542852",
        "download": "https://exe.io/845ew3Z",
        "media": "https://www.mediafire.com/folder/f3l1nznuafafz/serfclick.net",
        "date": 1763642216
    }
]